Metadata-Version: 1.1
Name: secure-file-detection
Version: 0.1.2
Summary: Detect true types of files.
Home-page: https://github.com/Myzel394/secure-file-detection
Author: Myzel394
Author-email: myzel394.xyllian@gmail.com
License: MIT
Download-URL: https://github.com/Myzel394/secure-file-detection/archieve/v_0.1.2.tar.gz
Keywords: detect-file,mimetype,detect-mime,real-type,file-type,file,type
Platform: UNKNOWN
Classifier: Programming Language :: Python :: 3.8
Classifier: Intended Audience :: Developers
Classifier: License :: OSI Approved :: MIT License
